{
    "/sharp.js": "/sharp.js?id=523253eeaceaf03b80c1",
    "/.bin/vendors.css": "/.bin/vendors.css?id=b2a0b102d03403904f14",
    "/sharp-cms.css": "/sharp-cms.css?id=8fc52805f7815b6b8413",
    "/.bin/vendor-components.css": "/.bin/vendor-components.css?id=9d581172a65abc8dc71f",
    "/vendor.js": "/vendor.js?id=afcdd10b0b96e56f761c",
    "/api.js": "/api.js?id=9c74f18bd5f7d29c2533",
    "/manifest.js": "/manifest.js?id=0225916a5d4fbc86a881",
    "/sharp.css": "/sharp.css?id=0c42c6064b998fc6348f"
}
